README.txt
buildout.cfg
setup.py
bootstrap/bootstrap.py
docs/HISTORY.txt
docs/INSTALL.txt
docs/LICENSE.GPL
docs/LICENSE.txt
grouparchy/__init__.py
grouparchy.schema.egg-info/PKG-INFO
grouparchy.schema.egg-info/SOURCES.txt
grouparchy.schema.egg-info/dependency_links.txt
grouparchy.schema.egg-info/entry_points.txt
grouparchy.schema.egg-info/namespace_packages.txt
grouparchy.schema.egg-info/not-zip-safe
grouparchy.schema.egg-info/requires.txt
grouparchy.schema.egg-info/top_level.txt
grouparchy/schema/__init__.py
grouparchy/schema/bbb.py
grouparchy/schema/configure.zcml
grouparchy/schema/event.py
grouparchy/schema/event.txt
grouparchy/schema/file.py
grouparchy/schema/interface.py
grouparchy/schema/interface.txt
grouparchy/schema/tests.py