Metadata-Version: 1.0
Name: grouparchy.schema
Version: 0.1
Summary: Grouparchy zope.schema extensions
Home-page: http://pypi.python.org/pypi/grouparchy.schema
Author: Ross Patterson
Author-email: me@rpatterson.net
License: GPL
Platform: UNKNOWN
Classifier: Framework :: Plone
Classifier: Framework :: Zope2
Classifier: Framework :: Zope3
Classifier: Programming Language :: Python
Classifier: Topic :: Software Development :: Libraries :: Python Modules
